etc/gitconfig/.gitconfig
etc/profile.d/git.sh
gitp/__init__.py
gitp/cli.py
gitp/metadata.py
gitp-0.2.5.data/data/bin/git-p
gitp-0.2.5.data/data/bin/git-top
gitp-0.2.5.data/data/etc/gh/config.yaml
gitp-0.2.5.dist-info/LICENSE
gitp-0.2.5.dist-info/METADATA
gitp-0.2.5.dist-info/WHEEL
gitp-0.2.5.dist-info/entry_points.txt
gitp-0.2.5.dist-info/top_level.txt
gitp-0.2.5.dist-info/RECORD
